zot2sioyek/__init__.py
zot2sioyek/zot2sioyek.py
zot2sioyek-0.4.1.dist-info/LICENSE
zot2sioyek-0.4.1.dist-info/METADATA
zot2sioyek-0.4.1.dist-info/WHEEL
zot2sioyek-0.4.1.dist-info/entry_points.txt
zot2sioyek-0.4.1.dist-info/top_level.txt
zot2sioyek-0.4.1.dist-info/RECORD
