Metadata-Version: 2.1
Name: zot2sioyek
Version: 0.4.1
Summary: Script with managing utils of zotero database fratures to sioyek PDF reader.
Author-email: Eduardo Toledo Campos <eduardotcampos@usp.br>
License: MIT License
Project-URL: Homepage, https://github.com/eduardotlc/zot2sioyek
Project-URL: Bug Reports, https://github.com/eduardotlc/zot2sioyek/issues
Project-URL: Source, https://github.com/eduardotlc/zot2sioyek/
Keywords: sioyek,zotero,PDF,reader,highlights
Classifier: Programming Language :: Python :: 3
Classifier: License :: OSI Approved :: MIT License
Classifier: Operating System :: OS Independent
Classifier: Topic :: Database
Classifier: Development Status :: 3 - Alpha
Requires-Python: >=3.8
License-File: LICENSE
Requires-Dist: pyzotero
Requires-Dist: pymupdf
Requires-Dist: PyQt5
Requires-Dist: regex
Requires-Dist: sioyek
Requires-Dist: httpx
Provides-Extra: test
Requires-Dist: pytest ; extra == 'test'
Requires-Dist: pytest-pretty ; extra == 'test'
Requires-Dist: interrogate ; extra == 'test'
